yarender/__init__.py
yarender/main.py
yarender-0.1.6.dist-info/entry_points.txt
yarender-0.1.6.dist-info/WHEEL
yarender-0.1.6.dist-info/METADATA
yarender-0.1.6.dist-info/RECORD
